odoo/addons/account_bank_statement_import_save_file/README.rst
odoo/addons/account_bank_statement_import_save_file/__init__.py
odoo/addons/account_bank_statement_import_save_file/__manifest__.py
odoo/addons/account_bank_statement_import_save_file/i18n/account_bank_statement_import_save_file.pot
odoo/addons/account_bank_statement_import_save_file/i18n/de.po
odoo/addons/account_bank_statement_import_save_file/i18n/es.po
odoo/addons/account_bank_statement_import_save_file/i18n/fi.po
odoo/addons/account_bank_statement_import_save_file/i18n/fr.po
odoo/addons/account_bank_statement_import_save_file/i18n/fr_CH.po
odoo/addons/account_bank_statement_import_save_file/i18n/gl.po
odoo/addons/account_bank_statement_import_save_file/i18n/hr.po
odoo/addons/account_bank_statement_import_save_file/i18n/it.po
odoo/addons/account_bank_statement_import_save_file/i18n/lt.po
odoo/addons/account_bank_statement_import_save_file/i18n/lt_LT.po
odoo/addons/account_bank_statement_import_save_file/i18n/nb_NO.po
odoo/addons/account_bank_statement_import_save_file/i18n/nl.po
odoo/addons/account_bank_statement_import_save_file/i18n/pt_BR.po
odoo/addons/account_bank_statement_import_save_file/i18n/pt_PT.po
odoo/addons/account_bank_statement_import_save_file/i18n/sl.po
odoo/addons/account_bank_statement_import_save_file/models/__init__.py
odoo/addons/account_bank_statement_import_save_file/models/account_bank_statement.py
odoo/addons/account_bank_statement_import_save_file/models/account_bank_statement_import.py
odoo/addons/account_bank_statement_import_save_file/readme/CONTRIBUTORS.rst
odoo/addons/account_bank_statement_import_save_file/readme/DESCRIPTION.rst
odoo/addons/account_bank_statement_import_save_file/readme/USAGE.rst
odoo/addons/account_bank_statement_import_save_file/static/description/icon.png
odoo/addons/account_bank_statement_import_save_file/static/description/index.html
odoo/addons/account_bank_statement_import_save_file/views/account_bank_statement.xml
odoo12_addon_account_bank_statement_import_save_file-12.0.1.0.0.99.dev7.dist-info/METADATA
odoo12_addon_account_bank_statement_import_save_file-12.0.1.0.0.99.dev7.dist-info/WHEEL
odoo12_addon_account_bank_statement_import_save_file-12.0.1.0.0.99.dev7.dist-info/top_level.txt
odoo12_addon_account_bank_statement_import_save_file-12.0.1.0.0.99.dev7.dist-info/RECORD
